predipy/__init__.py
predipy/config.py
predipy/predipy.py
predipy/preprocess/__init__.py
predipy/preprocess/encoder.py
predipy/preprocess/numeric.py
predipy/preprocess/text.py
predipy/utils/__init__.py
predipy/utils/io_helpers.py
predipy/utils/timing.py
predipy/utils/validation.py
predipy-0.2.0.dist-info/licenses/LICENSE
tests/__init__.py
tests/test_predipy.py
tests/test_preprocess.py
tests/test_utils.py
predipy-0.2.0.dist-info/METADATA
predipy-0.2.0.dist-info/WHEEL
predipy-0.2.0.dist-info/top_level.txt
predipy-0.2.0.dist-info/RECORD
