Metadata-Version: 2.4
Name: predipy
Version: 0.2.0
Summary: Lightweight Python library for prediction & regression
Home-page: https://example.com/
Author: Iyazkasep
Author-email: Iyaz.kasep2009@gmail.com
Classifier: Programming Language :: Python :: 3
Classifier: License :: OSI Approved :: MIT License
Classifier: Operating System :: OS Independent
Requires-Python: >=3.8
License-File: LICENSE
Dynamic: author-email
Dynamic: home-page
Dynamic: license-file
Dynamic: requires-python
